hemline/__init__.py
hemline/alignment.py
hemline/colors.py
hemline/defaults.py
hemline/frame.py
hemline/py.typed
hemline/themes.py
hemline/utils.py
hemline-1.1.0.dist-info/LICENSE.md
hemline-1.1.0.dist-info/METADATA
hemline-1.1.0.dist-info/WHEEL
hemline-1.1.0.dist-info/RECORD
