Metadata-Version: 2.1
Name: hemline
Version: 1.1.0
Summary: A python library for printing framed text to the terminal.
Author: Jonathan Herrera
Author-email: jonathan.herrera@posteo.de
Requires-Python: >=3.12,<4.0
Classifier: Programming Language :: Python :: 3
Classifier: Programming Language :: Python :: 3.12
Requires-Dist: mkdocs (>=1.6.1,<2.0.0)
Requires-Dist: tamal (>=0.1.3,<0.2.0)
Project-URL: docs, https://jnthnhrrr.github.io/python-hemline
Project-URL: issues, https://github.com/jnthnhrrr/python-hemline/issues
Project-URL: source, https://github.com/jnthnhrrr/python-hemline
